direct_deps/__init__.py
direct_deps/__main__.py
direct_deps/_version.py
direct_deps/distribution_metadata.py
direct_deps/import_analyzer.py
direct_deps/project_utils.py
direct_deps/py.typed
direct_deps/virtualenv_utils.py
direct_deps-0.0.4.dist-info/METADATA
direct_deps-0.0.4.dist-info/WHEEL
direct_deps-0.0.4.dist-info/entry_points.txt
direct_deps-0.0.4.dist-info/licenses/LICENSE
direct_deps-0.0.4.dist-info/licenses/LICENSE.txt
direct_deps-0.0.4.dist-info/RECORD
