Metadata-Version: 2.4
Name: direct-deps
Version: 0.0.4
Summary: A utility to analyze a Python project and its virtual environment to identify unused direct dependencies. Helps you keep your dependency list lean and accurate.
Project-URL: Documentation, https://github.com/FlavioAmurrioCS/direct-deps#readme
Project-URL: Issues, https://github.com/FlavioAmurrioCS/direct-deps/issues
Project-URL: Source, https://github.com/FlavioAmurrioCS/direct-deps
Author-email: Flavio Amurrio <25621374+FlavioAmurrioCS@users.noreply.github.com>
License-Expression: MIT
License-File: LICENSE
License-File: LICENSE.txt
Classifier: Development Status :: 4 - Beta
Classifier: Programming Language :: Python
Classifier: Programming Language :: Python :: 3.9
Classifier: Programming Language :: Python :: 3.10
Classifier: Programming Language :: Python :: 3.11
Classifier: Programming Language :: Python :: 3.12
Classifier: Programming Language :: Python :: 3.13
Classifier: Programming Language :: Python :: 3.14
Classifier: Programming Language :: Python :: Implementation :: CPython
Classifier: Programming Language :: Python :: Implementation :: PyPy
Requires-Python: >=3.9
Provides-Extra: tests
Requires-Dist: pytest; extra == 'tests'
Requires-Dist: tomli; (python_version < '3.11') and extra == 'tests'
Provides-Extra: types
Requires-Dist: mypy; extra == 'types'
Requires-Dist: pyrefly; extra == 'types'
Requires-Dist: pyright[nodejs]; extra == 'types'
Requires-Dist: pytest; extra == 'types'
Requires-Dist: tomli; (python_version < '3.11') and extra == 'types'
Requires-Dist: ty; extra == 'types'
Requires-Dist: typing-extensions; extra == 'types'
